{"TABLE": [[{"bbox": [[10.0, 439.8898], [550.0, 349.8898]]}]], "INVOICE_INFO": [], "BUYER": {"bbox": [[14.0, 629.4058000000001], [208.75999999999993, 713.4058]], "text": "Buyer :Michael Stewart\n53442 Marsh Falls\nEast Jacquelineside, KY 20462 US\nTel:+(462)423-2057\nEmail:crosbyrobert@example.org\nSite:http://richardson-weaver.org/"}, "DATE": {"bbox": [[266.0, 595.4058], [408.728, 607.4058]], "text": "Invoice Date: 17-Nov-2008"}, "DUE_DATE": {"bbox": [[14.0, 61.40576], [148.028, 73.40576]], "text": "Due Date : 01-Aug-1998"}, "NUMBER": {"bbox": [[266.0, 612.4058], [424.748, 624.4058]], "text": "Invoice number INV61173113"}, "PAYMENT_DETAILS": {"bbox": [[10.0, 248.2058], [239.40399999999997, 303.4058]], "text": "Bank Name           State Bank of England\nBranch Name          Raf CAMP\nBank Account Number  10375368\nBank Swift Code      SBININBB250"}, "SELLER_ADDRESS": {"bbox": [[16.0, 787.0058], [234.064, 813.4058]], "text": "Address:8508 Morgan Forge Suite 534\nNorth Michaelchester, VT 71194 US"}, "SELLER_NAME": {"bbox": [[16, 818], [175, 830]], "text": "Parker, Phillips and Thomas"}, "SUB_TOTAL": {"bbox": [[15.0, 140.4058], [166.36799999999994, 152.4058]], "text": "SUB_TOTAL : 630.47  USD"}, "TOTAL": {"bbox": [[151.0, 191.4058], [267.02799999999996, 203.4058]], "text": "TOTAL : 632.58 USD"}, "OTHER": {"text": "\u2018Contoso Entertainment System USA\n\nAddress:8508 Morgan Forge Suite 534\nNorth Michaelchester, VT 71194 US\n\nBuyer :Michael Stewart\n53442 Marsh Falls\nEast Jacquelineside, KY 20462 US\nTel:+(462)423-2057\nEmail:crosbyrobert@example.org\nSite: http://richardson-weaver.org/\nInvoice number INV61173113\n\nInvoice Date: 17-Nov-2008\n\nItem Price Quantity Amount\nBack usually. 26.85 6.00 161.10\nLikely begin new. 8.35 1.00 8.35\nPoor. 92.14 4.00 368.56\nSource himself. 30.82 3.00 92.46\nBank Name State Bank of England\nBranch Name Raf CAMP\n\nBank Account Number 10375368\nBank Swift Code SBININBB250\n\nTOTAL : 632.58 USD\n\nSUB_TOTAL : 630.47 USD\n\nDue Date : 01-Aug-1998\n"}, "LOGO": {"bbox": [[250, 841], [340, 751]]}}