{"TABLE": [[{"bbox": [[3.0, 282.88980000000004], [543.0, 174.8898]]}]], "INVOICE_INFO": [], "BILL_TO": {"bbox": [[44.0, 588.4127999999997], [204.79800000000006, 678.6128]], "text": "BILL_TO:\nAmanda Williams\n03179 Hartman Trace Apt. 844\nEast Richardville, TX 11872 US\nTel:+(474)539-9750\nEmail:hpeters@example.org\nSite:https://www.mathews.biz/"}, "DATE": {"bbox": [[428.0, 769.4058], [570.056, 781.4058]], "text": "Invoice Date: 08-Mar-2004"}, "NUMBER": {"bbox": [[346.0, 718.4058], [477.38800000000003, 730.4058]], "text": "INVOICE # 6Y1M8d-149"}, "TITLE": {"bbox": [[348.0, 798.1638], [551.004, 816.1638]], "text": "COMMERCIAL INVOICE"}, "GSTIN": {"bbox": [[7.0, 358.0058], [115.03599999999999, 384.4058]], "text": "GSTIN Code\nT2ABCDEI24322E4"}, "SEND_TO": {"bbox": [[329.0, 588.4127999999997], [501.117, 678.6128]], "text": "SHIP_TO:\nJoseph Morgan\n3881 Trujillo Rest Apt. 579\nPort Maryport, IL 44357 US\nTel:+(960)125-0141\nEmail:smithashley@example.org\nSite:https://www.morris.com/"}, "OTHER": {"text": "BILL_TO:\n\nAmanda Williams\n\n03179 Hartman Trace Apt. 844\nEast Richardville, TX 11872 US\nTel:+(474)539-9750\nEmail:hpeters@example.org\nSite:https://www.mathews.biz/\n\nGSTIN Code\nT2ABCDEI24322E4\n\nImagine table.\nAccept analysis talk.\n\nWeight figure.\nQuickly itself picture.\nOperation court\n\nCOMMERCIAL INVOICE\n\nInvoice Date: 08-Mar-2004\n\nINVOICE # 6Y1M8d-149\n\nSHIP_TO:\n\nJoseph Morgan\n\n3881 Trujillo Rest Apt. 579\n\nPort Maryport, IL 44357 US\nTel:+(960)125-0141\nEmail:smithashley@example.org\nSite:https://www.morris.com/\n\n"}, "LOGO": {"bbox": [[250, 831], [340, 741]]}}