{"TABLE": [[{"bbox": [[37.0, 289.88980000000004], [587.0, 235.8898]]}]], "INVOICE_INFO": [], "DATE": {"bbox": [[421.0, 512.4058], [519.712, 524.4058]], "text": "Date: 22-Apr-1993"}, "DUE_DATE": {"bbox": [[36.0, 515.4058], [169.36799999999997, 527.4058]], "text": "Due Date : 03-Nov-2008"}, "NUMBER": {"bbox": [[335.0, 784.4058], [471.716, 796.4058]], "text": "INVOICE ID 1Y8M4d-178"}, "NOTE": {"bbox": [[39.0, 617.0058], [287.03999999999996, 643.4058]], "text": "Note: All payments to be made in cash.\nContact us for queries on these quotations."}, "SELLER_ADDRESS": {"bbox": [[38.0, 687.0058], [233.40800000000002, 713.4058]], "text": "Address:045 David Walk Suite 362\nEast Robert, NV 70596 US"}, "SELLER_NAME": {"bbox": [[38, 729], [135, 741]], "text": "Murphy-Gallegos"}, "TAX": {"bbox": [[356.0, 120.4058], [516.0319999999999, 132.4058]], "text": "TAX:VAT (3.28%):  2.72 USD"}, "TITLE": {"bbox": [[304.0, 821.1638], [507.004, 839.1638]], "text": "COMMERCIAL INVOICE"}, "TOTAL": {"bbox": [[437.0, 103.4058], [546.356, 115.4058]], "text": "TOTAL : 84.72 USD"}, "TOTAL_WORDS": {"bbox": [[38.0, 105.0058], [207.34399999999997, 131.4058]], "text": "Total in words:  eighty-four p-\noint seven two"}, "SEND_TO": {"bbox": [[370.0, 548.4127999999997], [546.99, 638.6128]], "text": "SHIP_TO:\nChristopher Mayer Jr.\n49815 Pitts Stream\nLake Stephanie, CA 98763 US\nTel:+(467)465-5588\nEmail:martinezjohn@example.org\nSite:https://www.davis.com/"}, "OTHER": {"text": "COMMERCIAL INVOICE\n\nINVOICE ID 1Y8M4d-178\n\nCloudtad india Private Limited\nAnieneye indrasteucture Project No.38\nAddress:045 David Walk Suite 362\nEast Robert, NV 70596 US\n\nNote: All payments to be made in cash. SHIP To:\n\nContact us for queries on these quotations. Christopher Mayer Jr.\n\n49815 Pitts Stream\n\nLake Stephanie, CA 98763 US\nTel:+(467)465-5588\nEmail:martinezjohn@example.org\nSite:https://www.davis.com/\n\nDue Date : 03-Nov-2008 Date: 22-Apr-1993\n\nITEMS QUANTITY PRICE\n\nCenter around relationship shake. $35.69\n\nTotal in words: eighty-four p- TAX:VAT (3.28%): 2.72 USD\noint seven two TOTAL : 84.72 USD\n"}, "LOGO": {"bbox": [[70, 841], [160, 751]]}}