{"TABLE": [[{"bbox": [[22.0, 525.8897999999999], [538.0, 471.8898]]}]], "INVOICE_INFO": [], "BUYER": {"bbox": [[313.0, 633.4058000000001], [503.716, 717.4058]], "text": "Bill to:Jenna Hayes\n547 James Mountain Apt. 637\nPort Jeffreytown, IN 13215 US\nTel:+(670)641-3772\nEmail:vballard@example.org\nSite:http://www.james-yates.com/"}, "CONDITIONS": {"bbox": [[23.0, 184.81980000000001], [302.52000000000004, 206.81980000000001]], "text": "Terms and Conditions\nwill be charged if payment is not made within the due date."}, "DATE": {"bbox": [[14.0, 758.4058], [154.06399999999996, 770.4058]], "text": "Invoice Date: 04-Apr-2022"}, "DISCOUNT": {"bbox": [[343.0, 400.4058], [500.356, 412.4058]], "text": "DISCOUNT(3.45%): (-)  7.51"}, "DUE_DATE": {"bbox": [[15.0, 739.4058], [147.03599999999997, 751.4058]], "text": "Due Date : 03-Feb-2021"}, "NUMBER": {"bbox": [[16.0, 776.4058], [152.06799999999996, 788.4058]], "text": "Invoice number 5612-831"}, "NOTE": {"bbox": [[22.0, 253.4058], [223.384, 265.4058]], "text": "Note:Total payment due in 14 days."}, "PAYMENT_DETAILS": {"bbox": [[24.0, 372.20580000000007], [243.396, 427.4058]], "text": "Bank Name           Central Bank of USA\nBranch Name          Raf CAMP\nBank Account Number  10356960\nBank Swift Code      SBININBB250"}, "SELLER_ADDRESS": {"bbox": [[37.0, 659.0058], [225.72399999999996, 685.4058]], "text": "Address:6479 Smith Causeway\nEast Camerontown, AS 38212 US"}, "SELLER_NAME": {"bbox": [[37, 688], [140, 700]], "text": "Richardson-Davis"}, "SUB_TOTAL": {"bbox": [[343.0, 423.4058], [494.36799999999994, 435.4058]], "text": "SUB_TOTAL : 217.67  EUR"}, "TAX": {"bbox": [[343.0, 379.4058], [503.0319999999999, 391.4058]], "text": "TAX:VAT (3.48%):  7.57 EUR"}, "TITLE": {"bbox": [[16.0, 811.1638], [90.016, 829.1638]], "text": "INVOICE"}, "TOTAL": {"bbox": [[343.0, 298.4058], [459.02799999999996, 310.4058]], "text": "TOTAL : 222.63 EUR"}, "TOTAL_WORDS": {"bbox": [[313.0, 244.00579999999997], [540.352, 270.4058]], "text": "Total in words:  two hundred and twent-\ny-two point six three"}, "OTHER": {"text": "INVOICE\n\nInvoice number 5612-831\nInvoice Date: 04-Apr-2022\nDue Date : 03-Feb-2021\n\nBill to: Jenna Hayes\n\nAlexander Williams 547 James Mountain Apt. 637\nAddress:6479 Smith Causeway Port Jeffreytown, IN 13215 US\nEast Camerontown, AS 38212 US Tel:+(670)641-3772\n\nEmail:vballard@example.org\nSite:http://www.james-yates.com/\n\na\n\n}6.00 | 205473 Represent pretty half. 24.29 145.74\n\nBank Name Central Bank of USA SUB_TOTAL 2217-87\u2019 EUR\n\nBranch Name Raf CAMP DISCOUNT(3.45%): (-) 7.51\nBank Account Number 10356960 2 7%:\nBank Swift Code SBININBB250 TARA [9 Sia): Y-87 EUR\n\nTOTAL : 222.63 EUR\n\nNote:Total payment due in 14 days. Total in words: two hundred and twent-\ny-two point six three\n\nTerms and Conditions\nwill be charged if payment is not made within the due date.\n"}, "LOGO": {"bbox": [[505, 841], [595, 751]]}}