{"TABLE": [[{"bbox": [[14.0, 349.8898], [554.0, 295.8898]]}]], "INVOICE_INFO": [], "BUYER": {"bbox": [[14.0, 549.4058000000001], [226.70000000000005, 633.4058]], "text": "Buyer :Edward Lewis\n1430 Garcia Burgs Apt. 153\nKimberlychester, OK 82469 US\nTel:+(405)856-8644\nEmail:davisjennifer@example.com\nSite:https://www.carey-ferguson.info/"}, "DATE": {"bbox": [[299.0, 783.4058], [439.736, 795.4058]], "text": "Invoice Date: 10-Jan-2009"}, "DUE_DATE": {"bbox": [[299.0, 765.4058], [433.028, 777.4058]], "text": "Due Date : 19-Aug-2005"}, "NUMBER": {"bbox": [[300.0, 798.4058], [431.38800000000003, 810.4058]], "text": "INVOICE # 4Y1M8d-087"}, "NOTE": {"bbox": [[17.0, 87.0058], [265.03999999999996, 113.4058]], "text": "Note: All payments to be made in cash.\nContact us for queries on these quotations."}, "PAYMENT_DETAILS": {"bbox": [[16.0, 199.20579999999998], [244.084, 254.4058]], "text": "Bank Name           Central Bank of Texas\nBranch Name          Raf CAMP\nBank Account Number  19138701\nBank Swift Code      SBININBB250"}, "SELLER_ADDRESS": {"bbox": [[16.0, 689.0058], [188.72799999999995, 715.4058]], "text": "Address:9950 Santos Squares\nGarzafurt, MH 31937 US"}, "SELLER_EMAIL": {"bbox": [[119.0, 673.4058], [296.096, 685.4058]], "text": "Email:ospencer@example.com"}, "SELLER_NAME": {"bbox": [[17, 727], [85, 739]], "text": "Brooks LLC"}, "SELLER_SITE": {"bbox": [[14, 660], [137, 672]], "text": "www.BrooksLLC.com"}, "SUB_TOTAL": {"bbox": [[360.0, 246.4058], [492.70799999999997, 258.4058]], "text": "SUB_TOTAL : 701.19  $"}, "TOTAL": {"bbox": [[360.0, 186.9918], [528.812, 200.9918]], "text": "BALANCE DUE : 708.99 $"}, "TOTAL_WORDS": {"bbox": [[16.0, 137.0058], [232.04799999999994, 163.4058]], "text": "Total in words:  seven hundred and e-\night point nine nine"}, "GST(9%)": {"bbox": [[360.0, 213.4058], [454.03200000000004, 225.4058]], "text": "GST(9%) : 63.11"}, "OTHER": {"text": "INVOICE # 4Y1M8d-087\nInvoice Date: 10-Jan-2009\n\nDue Date : 19-Aug-2005\n\nCatalystK Company\n\nAddress:9950 Santos Squares\nGarzafurt, MH 31937 US\n\nEmail:ospencer@example.com\nWeb: www.catalystkkk.cor\n\nBuyer :Edward Lewis\n\n1430 Garcia Burgs Apt. 153\nKimberlychester, OK 82469 US\nTel:+(405)856-8644\nEmail:davisjennifer@example.com\nSite:https://www.carey-ferguson.info/\n\n6.00 571614 | What approach. 98.61 591.66\nBank Name Central Bank of Texas SUB_TOTAL : 701.19 $\nBranch Name Raf CAMP\n\nBank Account Number 19138701 GST(9%) : 63.11\n\nBank Swift Code SBININBB250\nBALANCE DUE : 708.99 $\n\nTotal in words: seven hundred and e-\night point nine nine\n\nNote: All payments to be made in cash.\nContact us for queries on these quotations.\n"}, "LOGO": {"bbox": [[20, 836], [110, 746]]}}