{"TABLE": [[{"bbox": [[50.0, 348.88980000000004], [564.72, 228.8898]]}]], "INVOICE_INFO": [], "BUYER": {"bbox": [[10.0, 576.4058000000001], [186.42399999999998, 660.4058]], "text": "Bill to:Cynthia Mathews\n7558 Scott Vista Suite 618\nCampbellfurt, ND 10642 US\nTel:+(301)317-8127\nEmail:kenneth63@example.net\nSite:http://www.carter.com/"}, "DATE": {"bbox": [[446.0, 713.4058], [588.7280000000001, 725.4058]], "text": "Invoice Date: 11-Dec-2011"}, "NUMBER": {"bbox": [[306.0, 802.4058], [442.716, 814.4058]], "text": "INVOICE ID 4Y3M7d-108"}, "NOTE": {"bbox": [[305.0, 766.0058], [573.0559999999999, 792.4058]], "text": "Note:\nThis order is shipped through blue dart courier"}, "SELLER_ADDRESS": {"bbox": [[12.0, 766.0058], [232.74, 792.4058]], "text": "Address:223 Kristen Mission Suite 986\nHernandezport, DE 40016 US"}, "SELLER_EMAIL": {"bbox": [[11.0, 690.4058], [189.44, 702.4058]], "text": "Email:rivassarah@example.org"}, "SELLER_NAME": {"bbox": [[12, 801], [71, 813]], "text": "Patel-Reid"}, "SUB_TOTAL": {"bbox": [[310.0, 23.40576], [461.36799999999994, 35.40576]], "text": "SUB_TOTAL : 569.05  USD"}, "TITLE": {"bbox": [[261.0, 820.1638], [376.02, 838.1638]], "text": "TAX INVOICE"}, "OTHER": {"text": "TAX INVOICE\n\nAXFORD PAINT PREMIERS PRIVATE LIMITED INVOICE ID 4Y3M7d-108\nAddress:223 Kristen Mission Suite 986 Note:\nHernandezport, DE 40016 US This order is shipped through blue dart courier\n\nInvoice Date: 11-Dec-2011\n\nEmail:rivassarah@example.org\n\nBill to:Cynthia Mathews\n\n7558 Scott Vista Suite 618\nCampbellfurt, ND 10642 US\nTel:+(301)317-8127\nEmail:kenneth63@example.net\nSite:http://www.carter.com/\n\n# ID Item name Quantity Unit price Amount\n1 606859 Protect his. 4.00 $1410 $56.40\n2 | 684579 Growth material. 1.00 $33.07 $33.07\n3 | 706531 Back voice apply. 6.00 $79.93 $479.58\n\nSUB_TOTAL : 569.05 USD\n"}, "LOGO": {"bbox": [[320, 741], [410, 651]]}}