{"TABLE": [[{"bbox": [[16.0, 469.8898], [566.0, 361.8898]]}]], "INVOICE_INFO": [], "DATE": {"bbox": [[381.0, 761.4058], [523.068, 773.4058]], "text": "Invoice Date: 11-Feb-2005"}, "DISCOUNT": {"bbox": [[279.0, 299.4058], [443.02799999999996, 311.4058]], "text": "DISCOUNT(4.64%): (-)  15.29"}, "DUE_DATE": {"bbox": [[380.0, 741.4058], [514.04, 753.4058]], "text": "Due Date : 04-May-1995"}, "NUMBER": {"bbox": [[380.0, 780.4058], [493.38800000000003, 792.4058]], "text": "INVOICE # 4997-198"}, "NOTE": {"bbox": [[14.0, 202.4058], [182.03599999999997, 214.4058]], "text": "Thank you for your business!"}, "SELLER_EMAIL": {"bbox": [[295.0, 40.40576], [490.072, 52.40576]], "text": "Email:scottoconnor@example.org"}, "TAX": {"bbox": [[279.0, 280.4058], [427.044, 292.4058]], "text": "TAX:VAT (3.32%):  10.93 $"}, "TOTAL": {"bbox": [[278.0, 221.4058], [375.368, 233.4058]], "text": "TOTAL : 329.43 $"}, "SEND_TO": {"bbox": [[279.0, 558.4127999999997], [459.059, 648.6128]], "text": "SHIP_TO:\nLeslie Miller\n5149 Turner Road Suite 039\nJohnstonhaven, ME 27730 US\nTel:+(659)123-9910\nEmail:tuckerronald@example.com\nSite:http://www.weber.org/"}, "OTHER": {"text": "INVOICE # 4997-198\nInvoice Date: 11-Feb-2005\nDue Date : 04-May-1995\n\nSHIP_TO:\n\nLeslie Miller\n\n5149 Turner Road Suite 039\nJohnstonhaven, ME 27730 US\nTel:+(659)123-9910\nEmail:tuckerronald@example.com\nSite:http://www.weber.org/\n\nDescription QUANTITY PRICE\nBar together cold. 1.00 $20.33\nStyle establish. 5.00 $13.80\nAlmost beyond difficult. 1.00 $51.50\nAvoid sit. 1.00 $31.30\nWhile easy camera. 2.00 $78.67\n\nThank you for your business!\n\nDISCOUNT(4.64%): (-) 15.29\nTAX:VAT (3.32%): 10.93 $\n\nTOTAL : 329.43 $\n\nEmail:scottoconnor@example.org\n\n"}, "LOGO": {"bbox": [[70, 811], [160, 721]]}}