{"TABLE": [[{"bbox": [[28.0, 320.8898], [544.0, 266.8898]]}]], "INVOICE_INFO": [], "BUYER": {"bbox": [[26.0, 521.4058000000001], [242.432, 605.4058]], "text": "Buyer :Samuel Sanders\n8101 Mason Flat\nCourtneychester, ND 23121 US\nTel:+(846)361-9982\nEmail:benjaminparsons@example.net\nSite:https://smith-blevins.com/"}, "DATE": {"bbox": [[393.0, 555.4058], [493.704, 567.4058]], "text": "Date: 22-Mar-2010"}, "NUMBER": {"bbox": [[393.0, 576.4058], [529.716, 588.4058]], "text": "INVOICE ID 2Y7M3d-772"}, "NOTE": {"bbox": [[23.0, 13.005759999999999], [271.03999999999996, 39.40576]], "text": "Note: All payments to be made in cash.\nContact us for queries on these quotations."}, "PO_NUMBER": {"bbox": [[393.0, 535.6128], [472.464, 546.6128]], "text": "PO Number :80"}, "SELLER_NAME": {"bbox": [[184, 797], [345, 809]], "text": "Phillips, Thomas and Malone"}, "SUB_TOTAL": {"bbox": [[349.0, 218.4058], [500.36799999999994, 230.4058]], "text": "SUB_TOTAL : 388.10  USD"}, "TAX": {"bbox": [[349.0, 187.4058], [515.704, 199.4058]], "text": "TAX:VAT (6.09%):  23.64 USD"}, "TITLE": {"bbox": [[343.0, 822.1638], [417.01599999999996, 840.1638]], "text": "INVOICE"}, "TOTAL": {"bbox": [[350.0, 96.40576], [466.02799999999996, 108.40576]], "text": "TOTAL : 403.55 USD"}, "OTHER": {"text": "INVOICE\n\nAFC Enterprises\n\nBuyer :Samuel Sanders\n\n8101 Mason Flat INVOICE ID 2Y7M3d-772\nCourtneychester, ND 23121 US\n\nTel:+(846)361-9982 Date.2e-Mar 2010\nEmail:benjaminparsons@example.net PO Number :80\nSite:https://smith-blevins.com/\n\na\n\n502807 Be buy what. 74.10 370.50\n594952 Image difference. 17.60\n\nSUB_TOTAL : 388.10 USD\n\nTAX:VAT (6.09%): 23.64 USD\n\nTOTAL : 403.55 USD\n\nNote: All payments to be made in cash.\nContact us for queries on these quotations.\n"}, "LOGO": {"bbox": [[380, 811], [470, 721]]}}