{"TABLE": [[{"bbox": [[16.0, 433.8898], [566.0, 361.8898]]}]], "INVOICE_INFO": [], "DATE": {"bbox": [[381.0, 761.4058], [481.716, 773.4058]], "text": "Date: 23-Feb-2001"}, "DISCOUNT": {"bbox": [[279.0, 299.4058], [436.356, 311.4058]], "text": "DISCOUNT(2.31%): (-)  11.4"}, "DUE_DATE": {"bbox": [[380.0, 741.4058], [512.036, 753.4058]], "text": "Due Date : 24-Jun-1999"}, "NUMBER": {"bbox": [[380.0, 780.4058], [525.392, 792.4058]], "text": "INVOICE ID INV/53-82/483"}, "NOTE": {"bbox": [[14.0, 202.4058], [182.03599999999997, 214.4058]], "text": "Thank you for your business!"}, "SELLER_EMAIL": {"bbox": [[295.0, 40.40576], [490.072, 52.40576]], "text": "Email:scottoconnor@example.org"}, "TAX": {"bbox": [[279.0, 280.4058], [445.70399999999995, 292.4058]], "text": "TAX:VAT (5.65%):  27.86 USD"}, "TOTAL": {"bbox": [[278.0, 221.4058], [394.02799999999996, 233.4058]], "text": "TOTAL : 502.05 USD"}, "SEND_TO": {"bbox": [[279.0, 558.4127999999997], [446.84900000000005, 648.6128]], "text": "SHIP_TO:\nMichelle Nelson\n74293 Carlos Inlet\nPort Jefferyhaven, CA 55549 US\nTel:+(917)669-4715\nEmail:ramoskayla@example.net\nSite:http://www.michael.biz/"}, "OTHER": {"text": "INVOICE ID INV/53-82/483\nDate: 23-Feb-2001\nDue Date : 24-Jun-1999\n\nSHIP_TO:\n\nMichelle Nelson\n\n74293 Carlos Inlet\n\nPort Jefferyhaven, CA 55549 US\nTel:+(917)669-4715\nEmail:ramoskayla@example.net\nSite:http://www.michael.biz/\n\nDescription QUANTITY PRICE\nImportant. 5.00 $27.29\nMorning voice. 4.00 $13.63\nAsk will page. 6.00 $50.42\n\nThank you for your business!\n\nDISCOUNT(2.31%): (-) 11.4\nTAX:VAT (5.65%): 27.86 USD\n\nTOTAL : 502.05 USD\n\nEmail:scottoconnor@example.org\n\n"}, "LOGO": {"bbox": [[70, 811], [160, 721]]}}