{"TABLE": [[{"bbox": [[50.0, 348.88980000000004], [564.72, 228.8898]]}]], "INVOICE_INFO": [], "BUYER": {"bbox": [[10.0, 576.4058000000001], [195.76000000000002, 660.4058]], "text": "Bill to:Tara Waller\n3304 Helen Green Apt. 291\nEast Sherylfort, NH 73424 US\nTel:+(142)080-6378\nEmail:rogerjones@example.com\nSite:http://www.jones.com/"}, "DATE": {"bbox": [[446.0, 713.4058], [588.74, 725.4058]], "text": "Invoice Date: 14-Aug-2019"}, "NUMBER": {"bbox": [[306.0, 802.4058], [446.064, 814.4058]], "text": "INVOICE # INV/27-16/831"}, "NOTE": {"bbox": [[305.0, 766.0058], [573.0559999999999, 792.4058]], "text": "Note:\nThis order is shipped through blue dart courier"}, "SELLER_ADDRESS": {"bbox": [[12.0, 766.0058], [232.74, 792.4058]], "text": "Address:223 Kristen Mission Suite 986\nHernandezport, DE 40016 US"}, "SELLER_EMAIL": {"bbox": [[11.0, 690.4058], [189.44, 702.4058]], "text": "Email:rivassarah@example.org"}, "SELLER_NAME": {"bbox": [[12, 801], [71, 813]], "text": "Patel-Reid"}, "SUB_TOTAL": {"bbox": [[310.0, 23.40576], [442.70799999999997, 35.40576]], "text": "SUB_TOTAL : 215.54  $"}, "TITLE": {"bbox": [[261.0, 820.1638], [464.004, 838.1638]], "text": "COMMERCIAL INVOICE"}, "OTHER": {"text": "COMMERCIAL INVOICE\nINVOICE # INV/27-16/831\n\nAXFORD PAINT PREMIERS PRIVATE LIMITED\n\nAddress:223 Kristen Mission Suite 986\nHernandezport, DE 40016 US\n\nEmail:rivassarah@example.org\n\nBill to:Tara Waller\n\n3304 Helen Green Apt. 291\n\nEast Sherylfort, NH 73424 US\nTel:+(142)080-6378\nEmail:rogerjones@example.com\nSite:http:/www.jones.com/\n\nNote:\n\nThis order is shipped through blue dart courier\n\nInvoice Date: 14-Aug-2019\n\n# ID Item name Quantity Unit price Amount\n1 257061 Whether south. 5.00 $5.61 $28.05\n2 | 190886 None body. 2.00 $70.69 $141.38\n3 716748 Six allow war begin. 3.00 $15.37 $46.11\n\nSUB_TOTAL : 215.54 $\n\n"}, "LOGO": {"bbox": [[320, 741], [410, 651]]}}