{"TABLE": [[{"bbox": [[50.0, 348.88980000000004], [564.72, 228.8898]]}]], "INVOICE_INFO": [], "BUYER": {"bbox": [[10.0, 576.4058000000001], [204.41199999999998, 660.4058]], "text": "Bill to:Jessica Mann\n81192 Mitchell Park\nCooperfurt, VI 32224 US\nTel:+(355)824-0089\nEmail:robinsonpaul@example.org\nSite:https://www.greene.biz/"}, "DATE": {"bbox": [[446.0, 713.4058], [586.064, 725.4058]], "text": "Invoice Date: 25-Oct-2017"}, "NUMBER": {"bbox": [[306.0, 802.4058], [442.068, 814.4058]], "text": "INVOICE # INV22932519"}, "NOTE": {"bbox": [[305.0, 766.0058], [573.0559999999999, 792.4058]], "text": "Note:\nThis order is shipped through blue dart courier"}, "SELLER_ADDRESS": {"bbox": [[12.0, 766.0058], [232.74, 792.4058]], "text": "Address:223 Kristen Mission Suite 986\nHernandezport, DE 40016 US"}, "SELLER_EMAIL": {"bbox": [[11.0, 690.4058], [189.44, 702.4058]], "text": "Email:rivassarah@example.org"}, "SELLER_NAME": {"bbox": [[12, 801], [71, 813]], "text": "Patel-Reid"}, "SUB_TOTAL": {"bbox": [[310.0, 23.40576], [442.70799999999997, 35.40576]], "text": "SUB_TOTAL : 486.78  $"}, "TITLE": {"bbox": [[261.0, 820.1638], [376.02, 838.1638]], "text": "TAX INVOICE"}, "OTHER": {"text": "TAX INVOICE\n\nAXFORD PAINT PREMIERS PRIVATE LIMITED INVOICE # INV22932519\nAddress:223 Kristen Mission Suite 986 Note:\nHernandezport, DE 40016 US This order is shipped through blue dart courier\n\nInvoice Date: 25-Oct-2017\n\nEmail:rivassarah@example.org\n\nBill to:Jessica Mann\n\n81192 Mitchell Park\n\nCooperfurt, VI 32224 US\nTel:+(355)824-0089\nEmail:robinsonpaul@example.org\nSite:https://www.greene.biz/\n\n# ID Item name Quantity Unit price Amount\n1 | 872808 Gun discuss kind. 2.00 $12.78 $25.56\n\n2 709712 | Into major personal voice. 5.00 $59.25 $296.25\n3 108345 Throughout radio. 3.00 $54.99 $164.97\n\nSUB_TOTAL : 486.78 $\n"}, "LOGO": {"bbox": [[320, 741], [410, 651]]}}