{"TABLE": [[{"bbox": [[19.0, 334.8898], [559.0, 280.8898]]}]], "INVOICE_INFO": [], "BILL_TO": {"bbox": [[7.0, 527.4127999999997], [184.859, 617.6128]], "text": "BILL_TO:\nJeremy Thornton\n94045 Frazier Port\nNorth Tonyfurt, MN 43257 US\nTel:+(797)934-2639\nEmail:cindy90@example.org\nSite:https://stout-mccormick.com/"}, "DATE": {"bbox": [[267.0, 517.4058], [403.728, 529.4058]], "text": "Invoice Date: 09-Jul-1995"}, "DISCOUNT": {"bbox": [[316.0, 169.4058], [473.356, 181.4058]], "text": "DISCOUNT(2.11%): (-)  7.61"}, "DUE_DATE": {"bbox": [[267.0, 489.4058], [398.376, 501.4058]], "text": "Due Date : 12-Jan-2022"}, "NUMBER": {"bbox": [[269.0, 567.4058], [431.744, 579.4058]], "text": "Invoice number INV/01-60/300"}, "SELLER_ADDRESS": {"bbox": [[9.0, 744.0058], [218.41199999999998, 770.4058]], "text": "Address:938 Gonzalez Key Suite 573\nNew Anitaport, MN 04941 US"}, "SELLER_EMAIL": {"bbox": [[210.0, 729.4058], [381.76800000000003, 741.4058]], "text": "Email:susan62@example.com"}, "SELLER_SITE": {"bbox": [[210, 700], [410, 712]], "text": "www.PaulGibsonandAnderson.com"}, "SUB_TOTAL": {"bbox": [[315.0, 207.4058], [447.70799999999997, 219.4058]], "text": "SUB_TOTAL : 360.88  $"}, "TAX": {"bbox": [[315.0, 132.4058], [463.044, 144.4058]], "text": "TAX:VAT (5.69%):  20.54 $"}, "TITLE": {"bbox": [[18.0, 808.1638], [92.016, 826.1638]], "text": "INVOICE"}, "TOTAL": {"bbox": [[315.0, 95.40576], [412.368, 107.40576]], "text": "TOTAL : 370.49 $"}, "OTHER": {"text": "INVOICE\n\nAddress:938 Gonzalez Key Suite 573\nNew Anitaport, MN 04941 US\nEmail:susan62@example.com\n\ncraigslandscaping.com\n\nBILL_TO:\n\nJeremy Thornton\n\n94045 Frazier Port\n\nNorth Tonyfurt, MN 43257 US Invoice number INV/01-60/300\nTel:+(797)934-2639\n\nEmail:cindy90@example.org\n\nSite:https://stout-mccormick.com/ ;\nInvoice Date: 09-Jul-1995\n\nDue Date : 12-Jan-2022\n\nlaty in | Description | Unit price | Amoun\n\n220 [soars Reality interview very. 24.69 49.38\n5.00 | 370602 | Move put. 62.30 311.50\n\nSUB_TOTAL : 360.88 $\nDISCOUNT(2.11%): (-) 7.61\nTAX:VAT (5.69%): 20.54 $\n\nTOTAL : 370.49 $\n"}, "LOGO": {"bbox": [[505, 841], [595, 751]]}}