{"TABLE": [[{"bbox": [[22.0, 433.8898], [562.0, 361.8898]]}]], "INVOICE_INFO": [], "BUYER": {"bbox": [[339.0, 735.4058000000001], [552.36, 819.4058]], "text": "Bill to:Sharon Russell\n547 Baker Ranch\nPort Deannaberg, ME 67843 US\nTel:+(329)880-1910\nEmail:jason82@example.org\nSite:http://www.fletcher-morrow.com/"}, "DATE": {"bbox": [[416.0, 639.4058], [518.708, 651.4058]], "text": "Date: 08-May-1997"}, "NUMBER": {"bbox": [[416.0, 657.4058], [552.716, 669.4058]], "text": "INVOICE ID 8Y6M3d-834"}, "NOTE": {"bbox": [[21.0, 21.40576], [222.384, 33.40576]], "text": "Note:Total payment due in 14 days."}, "SELLER_ADDRESS": {"bbox": [[21.0, 772.0058], [251.748, 798.4058]], "text": "Address:047 Jackson Meadows Apt. 391\nPearsonmouth, OH 83042 US"}, "SUB_TOTAL": {"bbox": [[405.0, 172.4058], [556.3679999999999, 184.4058]], "text": "SUB_TOTAL : 531.34  USD"}, "TITLE": {"bbox": [[25.0, 654.1638], [99.016, 672.1638]], "text": "INVOICE"}, "TOTAL_WORDS": {"bbox": [[304.0, 205.0058], [511.3599999999999, 231.4058]], "text": "Total in words:  five hundred and th-\nirty-five point five"}, "GSTIN": {"bbox": [[21.0, 734.4058], [197.028, 746.4058]], "text": "GSTIN No. 24AADCP1453)/AZZ"}, "AMOUNT_DUE": {"bbox": [[363.0, 262.78479999999996], [571.365, 277.78479999999996]], "text": "BALANCE_DUE : 535.50 USD"}, "OTHER": {"text": "Address:047 Jackson Meadows Apt. 391\nPearsonmouth, OH 83042 US\n\nGSTIN No. 24AADCP1453)/AZZ\n\nINVOICE\n\nItem\nDifference.\n\nNice list simple.\nState story.\n\nNote:Total payment due in 14 days.\n\nPrice\n79.21\n19.46\n76.91\n\nBill to:Sharon Russell\n\n547 Baker Ranch\n\nPort Deannaberg, ME 67843 US\nTel:+(329)880-1910\nEmail:jason82@example.org\nSite:http://www.fletcher-morrow.com/\n\nINVOICE ID 8Y6M3d-834\nDate: 08-May-1997\n\nQuantity Amount\n5.00 396.05\n3.00 58.38\n1.00 76.91\n\nBALANCE_DUE : 535.50 USD\n\nTotal in words: five hundred and th-\nirty-five point five\n\nSUB_TOTAL : 531.34 USD\n"}, "LOGO": {"bbox": [[270, 691], [360, 601]]}}