{"TABLE": [[{"bbox": [[27.0, 495.8898], [527.0, 387.8898]]}]], "INVOICE_INFO": [], "BUYER": {"bbox": [[316.0, 699.4058000000001], [507.36400000000003, 783.4058]], "text": "Buyer :Stacie Wilcox\n285 Xavier Run\nEast Russell, FL 31522 US\nTel:+(634)082-0925\nEmail:jacob94@example.net\nSite:http://www.thomas-clark.org/"}, "DATE": {"bbox": [[36.0, 621.4058], [137.376, 633.4058]], "text": "Date: 23-Dec-2002"}, "DUE_DATE": {"bbox": [[301.0, 637.4058], [433.036, 649.4058]], "text": "Due Date : 25-Jun-2006"}, "NUMBER": {"bbox": [[36.0, 639.4058], [172.06799999999996, 651.4058]], "text": "Invoice number 7856-603"}, "SELLER_ADDRESS": {"bbox": [[36.0, 708.0058], [249.42000000000002, 734.4058]], "text": "Address:6030 Willie Shores Suite 354\nGuerraton, TX 60058 US"}, "SELLER_EMAIL": {"bbox": [[35.0, 693.4058], [211.424, 705.4058]], "text": "Email:meghan88@example.net"}, "SELLER_NAME": {"bbox": [[36, 739], [99, 751]], "text": "Kelly-Moss"}, "SUB_TOTAL": {"bbox": [[323.0, 284.4058], [474.36799999999994, 296.4058]], "text": "SUB_TOTAL : 432.14  EUR"}, "TOTAL": {"bbox": [[324.0, 47.40576], [440.02799999999996, 59.40576]], "text": "TOTAL : 434.15 EUR"}, "GST(1%)": {"bbox": [[324.0, 87.40576], [411.36, 99.40576]], "text": "GST(1%) : 4.32"}, "GST(20%)": {"bbox": [[322.0, 125.4058], [422.704, 137.4058]], "text": "GST(20%) : 86.43"}, "GST(18%)": {"bbox": [[322.0, 168.4058], [422.704, 180.4058]], "text": "GST(18%) : 77.79"}, "GST(12%)": {"bbox": [[322.0, 205.4058], [422.704, 217.4058]], "text": "GST(12%) : 51.86"}, "GST(5%)": {"bbox": [[322.0, 244.4058], [416.03200000000004, 256.4058]], "text": "GST(5%) : 21.61"}, "OTHER": {"text": "Buyer :Stacie Wilcox\n\n285 Xavier Run\nlan Elliott East Russell, FL 31522 US\nAddress:6030 Willie Shores Suite 354 Tel:#(34)062-0928\nGuerraton, TX 60058 US Email:jacob94@example.net\n\nEmail:meghan88@example.net Site:http://www.thomas-clark.org/\n\nInvoice number 7856-603 Due Date : 25-Jun-2006\nDate: 23-Dec-2002\n\nem Price @ ANaateloia\nThird couple. $39.94 6.00 $239.64\nFactor able. $0.20 2.00 $0.40\nRisk old. $12.04 5.00 $60.20\nAnd. $59.70 2.00 $119.40\nWhile dream course pull. $12.50 1.00 $12.50\n\nSUB_TOTAL : 432.14 EUR\n\nGST(5%) : 21.61\n\nGST(12%) : 51.86\n\nGST(18%) : 77.79\n\nGST(20%) : 86.43\n\nGST(1%) : 4.32\n\nTOTAL : 434.15 EUR\n"}, "LOGO": {"bbox": [[20, 841], [110, 751]]}}