{"TABLE": [[{"bbox": [[27.0, 424.8898], [567.0, 316.8898]]}]], "INVOICE_INFO": [], "CONDITIONS": {"bbox": [[27.0, 52.819759999999995], [328.22, 98.81976]], "text": "Terms & Conditions\n1. Please send payment within 8 days of receiving this invoice.\nThere will be a 2.5% interest charge per month on late invoices.\n2. Please include the Invoice number in your payment notes."}, "DATE": {"bbox": [[28.0, 712.4058], [127.38399999999999, 724.4058]], "text": "Date: 22-Jan-2003"}, "NUMBER": {"bbox": [[28.0, 730.4058], [164.06799999999998, 742.4058]], "text": "INVOICE # INV83490394"}, "SUB_TOTAL": {"bbox": [[336.0, 239.4058], [468.70799999999997, 251.4058]], "text": "SUB_TOTAL : 643.46  $"}, "TITLE": {"bbox": [[250.0, 810.1638], [324.01599999999996, 828.1638]], "text": "INVOICE"}, "TOTAL_WORDS": {"bbox": [[27.0, 222.0058], [226.368, 248.4058]], "text": "Total in words:  six hundred and fi-\nfty point four six"}, "SEND_TO": {"bbox": [[338.0, 565.4127999999997], [498.501, 655.6128]], "text": "SHIP_TO:\nJasmine Warren\n41406 Ethan Cliff\nSouth Anthony, OK 77334 US\nTel:+(169)761-6158\nEmail:jennifer50@example.org\nSite:http://cisneros.org/"}, "OTHER": {"text": "INVOICE # INV83490394\nDate: 22-Jan-2003\n\nINVOICE\n\nSHIP_TO:\nJasmine Warren\n41406 Ethan Cliff\n\nSouth Anthony, OK 77334 US\n\nTel:+(169)761-6158\n\nEmail:jennifers50@example.org\n\nSite:http://cisneros.org/\n\nQty Description Unit Price Amount\n1.00 Actually political. 28.12 28.12\n6.00 Choice specific. 32.17 193.02\n3.00 Reason career outside. 75.62 226.86\n2.00 Culture should. 67.64 135.28\n2.00 Get pull away. 30.09 60.18\n\nTotal in words: six hundred and fi-\nfty point four six\n\nTerms & Conditions\n1. Please send payment within 8 days of receiving this invoice.\nThere will be a 2.5% interest charge per month on late invoices.\n2. Please include the Invoice number in your payment notes.\n\nSUB_TOTAL : 643.46 $\n\n"}, "LOGO": {"bbox": [[260, 801], [350, 711]]}}