{"TABLE": [[{"bbox": [[40.0, 537.8897999999999], [570.0, 357.8898]]}]], "INVOICE_INFO": [], "BILL_TO": {"bbox": [[40.0, 589.4127999999997], [239.87000000000003, 679.6128]], "text": "BILL_TO:\nMr. Jeffery Murray Jr.\n5843 Joseph Bridge\nWest Pedro, MS 58977 US\nTel:+(206)353-3548\nEmail:nwhite@example.org\nSite:https://www.mosley-cochran.info/"}, "DATE": {"bbox": [[221.0, 725.4058], [322.38800000000003, 737.4058]], "text": "Date: 22-Aug-1997"}, "DUE_DATE": {"bbox": [[403.0, 724.4058], [535.708, 736.4058]], "text": "Due Date : 17-Dec-2000"}, "NUMBER": {"bbox": [[39.0, 726.4058], [184.392, 738.4058]], "text": "INVOICE ID INV/91-88/722"}, "NOTE": {"bbox": [[38.0, 57.40576], [195.35599999999997, 69.40576]], "text": "Thank you for choosing us!"}, "PAYMENT_DETAILS": {"bbox": [[39.0, 96.2058], [252.40800000000002, 151.4058]], "text": "Bank Name            State Bank of India\nBranch Name          Raf CAMP\nBank Account Number  20000004512\nBank Swift Code      SBININBB250"}, "SELLER_ADDRESS": {"bbox": [[344.0, 600.0058], [516.068, 626.4058]], "text": "Address:98324 Espinoza View\nNorth Olivia, NY 66612 US"}, "SELLER_NAME": {"bbox": [[434, 656], [513, 666]], "text": "Morton-Leach"}, "SUB_TOTAL": {"bbox": [[346.0, 302.4058], [504.03999999999996, 314.4058]], "text": "SUB_TOTAL : 1100.03  USD"}, "TAX": {"bbox": [[347.0, 265.4058], [513.704, 277.4058]], "text": "TAX:VAT (5.01%):  55.06 USD"}, "TITLE": {"bbox": [[43.0, 789.1638], [246.004, 807.1638]], "text": "COMMERCIAL INVOICE"}, "TOTAL": {"bbox": [[346.0, 186.4058], [468.7, 198.4058]], "text": "TOTAL : 1112.52 USD"}, "OTHER": {"text": "COMMERCIAL INVOICE\n\nINVOICE ID INV/91-88/722 Date: 22-Aug-1997\n\nBILL_TO:\n\nMr. Jeffery Murray Jr.\n\n5843 Joseph Bridge\n\nWest Pedro, MS 58977 US\nTel:+(206)353-3548\nEmail:nwhite@example.org\nSite:https://www.mosley-cochran.info/\n\nITEMS QUANTITY\n\nDog note whole. 3.00\n\nTruth sort responsibility. 6.00\n\nApproach. 5.00\n\nHistory style reality. 1.00\n\nShe lawyer. 1.00\nBank Name State Bank of India\n\nBranch Name Raf CAMP\nBank Account Number 20000004512\nBank Swift Code SBININBB250\n\nThank you for choosing us!\n\nDue Date : 17-Dec-2000\n\nName\nCompany Name\n\nAddress:98324 Espinoza View\nNorth Olivia, NY 66612 US\n\nPRICE TAX AMOUNT\n81.56 $0.00 $244.68\n\n$51.94 $0.00 $311.64\n82.19 $0.00 $410.95\n78.98 $0.00 $78.98\n\n$53.78 $0.00 $53.78\n\nSUB_TOTAL : 1100.03 USD\n\nTAX:VAT (5.01%): 55.06 USD\n\nTOTAL : 1112.52 USD\n"}, "LOGO": {"bbox": [[505, 841], [595, 751]]}}