{"TABLE": [[{"bbox": [[2.0, 482.8898], [552.0, 392.8898]]}]], "INVOICE_INFO": [], "CONDITIONS": {"bbox": [[5.0, 147.81980000000001], [306.22, 193.81980000000001]], "text": "Terms & Conditions\n1. Please send payment within 8 days of receiving this invoice.\nThere will be a 2.5% interest charge per month on late invoices.\n2. Please include the Invoice number in your payment notes."}, "DATE": {"bbox": [[396.0, 724.4058], [536.736, 736.4058]], "text": "Invoice Date: 20-Jun-1995"}, "DUE_DATE": {"bbox": [[396.0, 712.4058], [527.376, 724.4058]], "text": "Due Date : 02-Jan-2018"}, "NUMBER": {"bbox": [[395.0, 740.4058], [535.0640000000001, 752.4058]], "text": "INVOICE # INV/84-89/110"}, "SELLER_ADDRESS": {"bbox": [[65.0, 781.0058], [255.068, 807.4058]], "text": "Address:496 Buck Rest Suite 598\nJenningsburgh, UT 95460 US"}, "SELLER_NAME": {"bbox": [[65, 807], [145, 819]], "text": "Jensen Group"}, "TITLE": {"bbox": [[274.0, 809.1638], [389.02, 827.1638]], "text": "TAX INVOICE"}, "SEND_TO": {"bbox": [[154.0, 603.4127999999997], [361.53700000000003, 693.6128]], "text": "SHIP_TO:\nKathryn Ramirez\n946 Kristie Inlet Suite 613\nPadillafort, NE 19922 US\nTel:+(505)180-2689\nEmail:jonathanthompson@example.org\nSite:https://www.martinez-stone.com/"}, "OTHER": {"text": "Gerald Wolf TAX INVOICE\n\nAddress:496 Buck Rest Suite 598\nJenningsburgh, UT 95460 US\n\nINVOICE # INV/84-89/110\n\nInvoice Date: 20-Jun-1995\nDue Date : 02-Jan-2018\n\nSHIP_TO:\n\nKathryn Ramirez\n\n946 Kristie Inlet Suite 613\n\nPadillafort, NE 19922 US\nTel:+(505)180-2689\nEmail:jonathanthompson@example.org\nSite:https://www.martinez-stone.com/\n\nDescription QUANTITY PRICE\nGeneral gas debate news. 3.00 $84.93\nSkill bring ask. 5.00 $15.29\nHere. 1.00 $89.21\nFront attention few. 5.00 $37.13\n\nTerms & Conditions\n\n1. Please send payment within 8 days of receiving this invoice.\nThere will be a 2.5% interest charge per month on late invoices.\n2. Please include the Invoice number in your payment notes.\n\n"}, "LOGO": {"bbox": [[30, 741], [120, 651]]}}