{"TABLE": [[{"bbox": [[3.0, 282.88980000000004], [543.0, 174.8898]]}]], "INVOICE_INFO": [], "BILL_TO": {"bbox": [[44.0, 588.4127999999997], [217.33800000000002, 678.6128]], "text": "BILL_TO:\nMelissa Beard\n0765 Todd Shore Apt. 552\nJosemouth, DC 80738 US\nTel:+(687)886-8085\nEmail:dorseycindy@example.org\nSite:http://erickson-arnold.info/"}, "DATE": {"bbox": [[428.0, 769.4058], [526.712, 781.4058]], "text": "Date: 30-Apr-2022"}, "NUMBER": {"bbox": [[346.0, 718.4058], [482.716, 730.4058]], "text": "INVOICE ID 7Y2M3d-258"}, "TITLE": {"bbox": [[348.0, 798.1638], [422.01599999999996, 816.1638]], "text": "INVOICE"}, "GSTIN": {"bbox": [[7.0, 358.0058], [115.03599999999999, 384.4058]], "text": "GSTIN Code\nT2ABCDEI24322E4"}, "SEND_TO": {"bbox": [[329.0, 588.4127999999997], [505.63800000000003, 678.6128]], "text": "SHIP_TO:\nAshley Conway\n699 Smith Falls Suite 037\nEast Hannah, MA 60060 US\nTel:+(372)791-1211\nEmail:carterjillian@example.org\nSite:http://www.luna-phillips.com/"}, "OTHER": {"text": "INVOICE\n\nDate: 30-Apr-2022\n\nINVOICE ID 7Y2M3d-258\n\nBILL_TO: SHIP_TO:\nMelissa Beard Ashley Conway\n0765 Todd Shore Apt. 552 699 Smith Falls Suite 037\nJosemouth, DC 80738 US East Hannah, MA 60060 US\nTel:+(687)886-8085 Tel:+(372)791-1211\nEmail:dorseycindy@example.org Email:carterjillian@example.org\nSite:http://erickson-arnold.info/ Site: http://www.luna-phillips.com/\nGSTIN Code\nT2ABCDEI24322E4\n\nlaty lin | Deseription | Unit price | Amoun\n\n289658 | Car organization.\n362924 | The short.\n\n758524 =| Call draw.\n\n"}, "LOGO": {"bbox": [[250, 831], [340, 741]]}}