{"TABLE": [[{"bbox": [[16.0, 433.8898], [566.0, 361.8898]]}]], "INVOICE_INFO": [], "DATE": {"bbox": [[381.0, 761.4058], [523.7280000000001, 773.4058]], "text": "Invoice Date: 11-Nov-1995"}, "DISCOUNT": {"bbox": [[279.0, 299.4058], [436.356, 311.4058]], "text": "DISCOUNT(3.36%): (-)  21.7"}, "DUE_DATE": {"bbox": [[380.0, 741.4058], [510.704, 753.4058]], "text": "Due Date : 18-Oct-2019"}, "NUMBER": {"bbox": [[380.0, 780.4058], [516.068, 792.4058]], "text": "Invoice number 9172-972"}, "NOTE": {"bbox": [[14.0, 202.4058], [171.35599999999997, 214.4058]], "text": "Thank you for choosing us!"}, "SELLER_EMAIL": {"bbox": [[295.0, 40.40576], [490.072, 52.40576]], "text": "Email:scottoconnor@example.org"}, "TAX": {"bbox": [[279.0, 280.4058], [445.70399999999995, 292.4058]], "text": "TAX:VAT (5.72%):  36.97 EUR"}, "TOTAL": {"bbox": [[278.0, 221.4058], [394.02799999999996, 233.4058]], "text": "TOTAL : 669.53 EUR"}, "SEND_TO": {"bbox": [[279.0, 558.4127999999997], [442.53700000000003, 648.6128]], "text": "SHIP_TO:\nColin Jones\n1692 Linda Canyon Apt. 680\nSouth Stephanie, SD 98386 US\nTel:+(864)912-4131\nEmail:jocompton@example.net\nSite:https://www.stewart.com/"}, "OTHER": {"text": "Invoice number 9172-972\nInvoice Date: 11-Nov-1995\nDue Date : 18-Oct-2019\n\nSHIP_TO:\n\nColin Jones\n\n1692 Linda Canyon Apt. 680\nSouth Stephanie, SD 98386 US\nTel:+(864)912-4131\nEmail:jocompton@example.net\nSite:https://www.stewart.com/\n\nDescription QUANTITY PRICE\nKid state. 5.00 $62.23\nSit forward structure. 1.00 $37.39\nPolicy class within. 4.00 $74.33\n\nThank you for choosing us!\n\nDISCOUNT(3.36%): (-) 21.7\nTAX:VAT (5.72%): 36.97 EUR\n\nTOTAL : 669.53 EUR\n\nEmail:scottoconnor@example.org\n\n"}, "LOGO": {"bbox": [[70, 811], [160, 721]]}}