{"TABLE": [[{"bbox": [[24.0, 288.88980000000004], [564.0, 234.8898]]}]], "INVOICE_INFO": [], "BILL_TO": {"bbox": [[23.0, 521.4127999999997], [199.38500000000002, 611.6128]], "text": "BILL_TO:\nWilliam Gonzales\n6027 Charles Cape Apt. 388\nWilsonburgh, CT 21790 US\nTel:+(235)212-0442\nEmail:suttoncorey@example.com\nSite:http://www.oliver.com/"}, "DATE": {"bbox": [[333.0, 562.4058], [433.716, 574.4058]], "text": "Date: 04-Feb-1995"}, "DUE_DATE": {"bbox": [[334.0, 507.4058], [467.368, 519.4058]], "text": "Due Date : 08-Nov-2013"}, "NUMBER": {"bbox": [[404.0, 598.4058], [562.748, 610.4058]], "text": "Invoice number INV42350070"}, "PO_NUMBER": {"bbox": [[216.0, 675.6128], [295.464, 686.6128]], "text": "PO Number :30"}, "SELLER_ADDRESS": {"bbox": [[173.0, 723.0058], [405.75200000000007, 749.4058]], "text": "Address:84945 Watson Greens Suite 097\nMaryshire, TX 73257 US"}, "SELLER_EMAIL": {"bbox": [[222.0, 695.4058], [423.108, 707.4058]], "text": "Email:milleramanda@example.com"}, "SELLER_NAME": {"bbox": [[215, 757], [290, 769]], "text": "White-Owens"}, "TITLE": {"bbox": [[111.0, 797.1638], [185.016, 815.1638]], "text": "INVOICE"}, "OTHER": {"text": "INVOICE\n\n\u2018Energy Efficiency Center\n\nAddress:84945 Watson Greens Suite 097\nMaryshire, TX 73257 US\n\nEmail:milleramanda@example.com\nPO Number :30\n\nBILL_TO: Invoice number INV42350070\nWilliam Gonzales\n\n6027 Charles Cape Apt. 388\n\nWilsonburgh, CT 21790 US Date: 04-Feb-1995\n\nTel:+(235)212-0442\n\nEmail:suttoncorey@example.com\n\nSite:http://www.oliver.com/\nDue Date : 08-Nov-2013\n\nQty Description Unit Price Amount\n6.00 Education since million. 15.51 93.06\n\n6.00 Probably every. 84.08 504.48\n\n"}, "LOGO": {"bbox": [[40, 771], [130, 681]]}}