{"TABLE": [[{"bbox": [[3.0, 426.8898], [543.0, 318.8898]]}]], "INVOICE_INFO": [], "BILL_TO": {"bbox": [[197.0, 529.4127999999997], [362.022, 619.6128]], "text": "BILL_TO:\nBrandy Vargas\n85305 Kimberly Cape\nEast Bethtown, SD 38850 US\nTel:+(302)425-3219\nEmail:stacy05@example.com\nSite:http://haynes-moreno.com/"}, "DATE": {"bbox": [[427.0, 711.4058], [569.7280000000001, 723.4058]], "text": "Invoice Date: 29-Dec-1994"}, "DUE_DATE": {"bbox": [[187.0, 441.4058], [319.708, 453.4058]], "text": "Due Date : 24-Sep-2008"}, "NUMBER": {"bbox": [[427.0, 688.4058], [563.068, 700.4058]], "text": "Invoice number 0367-335"}, "NOTE": {"bbox": [[11.0, 210.0058], [279.056, 236.4058]], "text": "Note:\nThis order is shipped through blue dart courier"}, "PO_NUMBER": {"bbox": [[426.0, 667.6128], [505.464, 678.6128]], "text": "PO Number :58"}, "SELLER_NAME": {"bbox": [[6, 765], [148, 777]], "text": "Kirk, Murphy and Daniels"}, "TAX": {"bbox": [[395.0, 232.4058], [561.704, 244.4058]], "text": "TAX:VAT (6.24%):  67.49 USD"}, "TITLE": {"bbox": [[243.0, 811.1638], [446.004, 829.1638]], "text": "COMMERCIAL INVOICE"}, "TOTAL": {"bbox": [[395.0, 209.4058], [517.7, 221.4058]], "text": "TOTAL : 1097.17 USD"}, "TOTAL_WORDS": {"bbox": [[294.0, 145.0058], [525.3599999999999, 171.4058]], "text": "Total in words:  one thousand and ninet-\ny-seven point one seven"}, "OTHER": {"text": "COMMERCIAL INVOICE\n\nNK.NAG & CO,\n\nInvoice Date: 29-Dec-1994\nInvoice number 0367-335\nPO Number :58\n\nBILL_TO:\n\nBrandy Vargas\n\n85305 Kimberly Cape\n\nEast Bethtown, SD 38850 US\nTel:+(302)425-3219\nEmail:stacy05@example.com\nSite:http://haynes-moreno.com/\n\nDue Date : 24-Sep-2008\n\n16.00 | 657347 _| Effect officer listen. 63.78 382.68\n835142 _| Talk southern wait. 26.67 106.68\n\n[4.00 | 955558 37.90 151.60\n16.00 | 584012 _| Back hold above. 49.26\n\n504988 _| Cold if. 97.76 391.04\n\nNote: TAX:VAT (6.24%): 67.49 USD\nThis order is shipped through blue dart courier TOTAL : 1097.17 USD\n\nTotal in words: one thousand and ninet-\ny-seven point one seven\n"}, "LOGO": {"bbox": [[5, 751], [95, 661]]}}