{"TABLE": [[{"bbox": [[6.0, 405.8898], [536.0, 285.8898]]}]], "INVOICE_INFO": [], "BUYER": {"bbox": [[300.0, 701.4058000000001], [457.764, 785.4058]], "text": "Bill to:Erika Frank\n50625 Beck Walks\nNorth Becky, IN 40247 US\nTel:+(606)051-2436\nEmail:pkelley@example.net\nSite:https://peterson.com/"}, "DATE": {"bbox": [[9.0, 827.4058], [110.37599999999999, 839.4058]], "text": "Date: 25-Nov-2022"}, "NUMBER": {"bbox": [[300.0, 828.4058], [431.38800000000003, 840.4058]], "text": "INVOICE # 3Y8M3d-358"}, "NOTE": {"bbox": [[8.0, 147.4058], [209.384, 159.4058]], "text": "Note:Total payment due in 14 days."}, "SELLER_ADDRESS": {"bbox": [[8.0, 728.0058], [172.748, 754.4058]], "text": "Address:5190 Perry Passage\nKellyburgh, RI 60615 US"}, "SELLER_EMAIL": {"bbox": [[9.0, 636.4058], [192.75600000000003, 648.4058]], "text": "Email:marymoore@example.org"}, "SELLER_NAME": {"bbox": [[8, 772], [59, 784]], "text": "Miller Inc"}, "SUB_TOTAL": {"bbox": [[332.0, 145.4058], [483.36799999999994, 157.4058]], "text": "SUB_TOTAL : 579.05  EUR"}, "TOTAL": {"bbox": [[334.0, 28.40576], [450.02799999999996, 40.40576]], "text": "TOTAL : 575.13 EUR"}, "OTHER": {"text": "Date: 25-Nov-2022\n\nLuke Bowers\n\nAddress:5190 Perry Passage\nKellyburgh, RI 60615 US\n\nEmail:marymoore@example.org\n\nITEMS\nMachine break page.\nWestern happy while guess.\n\nIndicate window teacher.\n\nNote:Total payment due in 14 days.\n\nQUANTITY\n\n1.00\n\n4.00\n\n2.00\n\nINVOICE # 3Y8M3d-358\n\nBill to:Erika Frank\n\n50625 Beck Walks\n\nNorth Becky, IN 40247 US\nTel:+(606)051-2436\nEmail:pkelley@example.net\nSite:https://peterson.com/\n\nPRICE TAX\n$62.79 $0.00\n$94.10 $0.00\n$69.93 $0.00\n\nAMOUNT\n\n$62.79\n\n$376.40\n\n$139.86\n\nSUB_TOTAL : 579.05 EUR\n\nTOTAL : 575.13 EUR\n"}, "LOGO": {"bbox": [[190, 826], [280, 736]]}}